{"__symbolic":"module","version":4,"metadata":{"IEnvVar":{"__symbolic":"interface"},"Process":{"__symbolic":"class","members":{"__ctor__":[{"__symbolic":"constructor","parameters":[{"__symbolic":"reference","name":"string"},{"__symbolic":"reference","module":"logviewer.client.toolkit","name":"IAPI","line":28,"character":56}]}],"commandStarted":[{"__symbolic":"method"}],"_ng_onKeyUp":[{"__symbolic":"method"}],"_sendInput":[{"__symbolic":"method"}],"_sendCommand":[{"__symbolic":"method"}],"_ng_onStop":[{"__symbolic":"method"}],"_sendStop":[{"__symbolic":"method"}]},"statics":{"_processSerial":0}},"SidebarVerticalComponent":{"__symbolic":"class","decorators":[{"__symbolic":"call","expression":{"__symbolic":"reference","module":"@angular/core","name":"Component","line":93,"character":1},"arguments":[{"selector":{"__symbolic":"select","expression":{"__symbolic":"reference","module":"logviewer.client.toolkit","name":"EViewsTypes","line":94,"character":14},"member":"sidebarVertical"},"template":"<div *ngIf=\"!_ng_ready\">\n    <lib-primitive-spinner-regular></lib-primitive-spinner-regular>\n</div>\n\n<div class=\"wrapper\" *ngIf=\"_ng_ready && _ng_settings !== undefined\">\n    <p class=\"t-normal\">Environment vars</p>\n    <ul class=\"env-vars\">\n        <li *ngFor=\"let envvar of _ng_envvars\">\n            <span class=\"key t-console\">{{envvar.key}}</span>\n            <span class=\"value t-console\">{{envvar.value}}</span>\n        </li>\n    </ul>\n    <p class=\"t-normal\">Shell</p>\n    <p class=\"t-console crop\">{{_ng_settings.shell}}</p>\n    <p class=\"t-normal\">Cwd</p>\n    <p class=\"t-console crop\">{{_ng_settings.cwd}}</p>\n</div>\n\n<ul *ngIf=\"_ng_ready\">\n    <li *ngFor=\"let process of _ng_processes\">\n        <div [attr.class]=\"'container ' + (process._ng_working ? 'working' : 'free')\">\n            <div class=\"comstyle-input-holder input-wrapper\">\n                <div class=\"comstyle-input\">\n                    <input #cmdinput\n                        class=\"comstyle-input\"\n                        [attr.disabled]=\"process._ng_working ? '' : null\"\n                        type=\"text\"\n                        placeholder=\"command or path to program to be executed\"\n                        [(ngModel)]=\"process._ng_cmd\"\n                        (keyup)=\"process._ng_onKeyUp($event)\"/>\n                </div>\n            </div>\n            <div class=\"buttons\" *ngIf=\"process._ng_working\">\n                <span class=\"small-button\" (click)=\"process._ng_onStop($event)\">Stop</span>\n            </div>\n            <div class=\"spinner\" *ngIf=\"process._ng_working\">\n                <lib-primitive-spinner-regular></lib-primitive-spinner-regular>\n            </div>\n        </div>\n        <span class=\"splitter\"></span>\n    </li>\n</ul>\n","styles":[":host{position:absolute;display:block;top:.5rem;left:.5rem;right:.5rem;bottom:.5rem;overflow-x:hidden;overflow-y:auto}:host div.wrapper{position:relative;display:block;width:100%}:host div.wrapper ul.env-vars{position:relative;display:block;padding:0;margin:0;list-style:none;max-height:15rem;overflow-x:hidden;overflow-y:auto}:host div.wrapper ul.env-vars li{position:relative;display:block;padding:0;margin:0;list-style:none;height:1rem;white-space:nowrap;border-bottom:thin dotted grey}:host div.wrapper ul.env-vars li *{display:inline-block;vertical-align:top;overflow:hidden;text-overflow:ellipsis}:host div.wrapper ul.env-vars li span.key{width:30%}:host div.wrapper ul.env-vars li span.value{width:70%}:host div.wrapper p.crop{font-size:.8rem;line-height:.8rem;font-family:console,monospace;height:1rem;overflow:hidden;text-overflow:ellipsis;white-space:pre}:host .container{position:relative;display:block;box-sizing:border-box;width:100%;overflow:hidden}:host .container div.input-wrapper{position:relative;display:block;height:1.5rem;width:calc(100% + 1rem);margin-left:-.5rem}:host .container.working div.input-wrapper{position:relative;display:block;height:1.5rem;width:calc(100% - 5.5rem);margin-left:2.5rem}:host .container.working .input-area{width:auto;margin-right:2.5rem}:host .container div.spinner{position:absolute;left:.25rem;top:.25rem;width:2rem;height:1rem}:host .container div.buttons{position:absolute;right:0;top:-.35rem;height:100%;width:3rem}"]}]}],"members":{"_ng_input":[{"__symbolic":"property","decorators":[{"__symbolic":"call","expression":{"__symbolic":"reference","module":"@angular/core","name":"ViewChild","line":101,"character":5},"arguments":["cmdinput"]}]}],"api":[{"__symbolic":"property","decorators":[{"__symbolic":"call","expression":{"__symbolic":"reference","module":"@angular/core","name":"Input","line":103,"character":5}}]}],"session":[{"__symbolic":"property","decorators":[{"__symbolic":"call","expression":{"__symbolic":"reference","module":"@angular/core","name":"Input","line":104,"character":5}}]}],"sessions":[{"__symbolic":"property","decorators":[{"__symbolic":"call","expression":{"__symbolic":"reference","module":"@angular/core","name":"Input","line":105,"character":5}}]}],"__ctor__":[{"__symbolic":"constructor","parameters":[{"__symbolic":"reference","module":"@angular/core","name":"ChangeDetectorRef","line":116,"character":32}]}],"ngOnDestroy":[{"__symbolic":"method"}],"ngAfterViewInit":[{"__symbolic":"method"}],"_onIncomeMessage":[{"__symbolic":"method"}],"_onIncomeEvent":[{"__symbolic":"method"}],"_settingsUpdated":[{"__symbolic":"method"}],"_onSessionChange":[{"__symbolic":"method"}],"_onSessionOpen":[{"__symbolic":"method"}],"_onSessionClose":[{"__symbolic":"method"}],"_saveState":[{"__symbolic":"method"}],"_loadState":[{"__symbolic":"method"}],"_initState":[{"__symbolic":"method"}],"_forceUpdate":[{"__symbolic":"method"}]}},"PluginModule":{"__symbolic":"class","extends":{"__symbolic":"reference","module":"logviewer.client.toolkit","name":"PluginNgModule","line":14,"character":34},"decorators":[{"__symbolic":"call","expression":{"__symbolic":"reference","module":"@angular/core","name":"NgModule","line":7,"character":1},"arguments":[{"entryComponents":[{"__symbolic":"reference","name":"SidebarVerticalComponent"}],"declarations":[{"__symbolic":"reference","name":"SidebarVerticalComponent"}],"imports":[{"__symbolic":"reference","module":"@angular/common","name":"CommonModule","line":10,"character":15},{"__symbolic":"reference","module":"@angular/forms","name":"FormsModule","line":10,"character":29},{"__symbolic":"reference","module":"logviewer-client-primitive","name":"PrimitiveModule","line":10,"character":42}],"exports":[{"__symbolic":"reference","name":"SidebarVerticalComponent"}]}]}],"members":{"__ctor__":[{"__symbolic":"constructor"}]}},"parserRow":{"__symbolic":"function"},"parserRest":{"__symbolic":"function"}},"origins":{"IEnvVar":"./lib/views/sidebar.vertical/component","Process":"./lib/views/sidebar.vertical/component","SidebarVerticalComponent":"./lib/views/sidebar.vertical/component","PluginModule":"./lib/module","parserRow":"./lib/parsers/parser.row","parserRest":"./lib/parsers/parser.rest"},"importAs":"processes"}